MANIFEST.in
README.md
requirements.txt
setup.py
celebi/__init__.py
celebi/__main__.py
celebi/__meta__.py
celebi/settings.py
celebi/utils.py
celebi.egg-info/PKG-INFO
celebi.egg-info/SOURCES.txt
celebi.egg-info/dependency_links.txt
celebi.egg-info/requires.txt
celebi.egg-info/top_level.txt
celebi/apis/__init__.py
celebi/core/__init__.py
celebi/core/decorators.py
celebi/core/types.py
celebi/core/wsgi.py
celebi/core/middleware/__init__.py
celebi/core/middleware/websocket.py
celebi/io/__init__.py
celebi/io/postgres/__init__.py
celebi/io/postgres/monitor.py
celebi/io/postgres/queryset.py
celebi/io/postgres/types.py
celebi/io/postgres/utils.py
celebi/io/qubit/__init__.py
celebi/io/qubit/entangle.py
celebi/io/qubit/measure.py
celebi/io/qubit/monitor.py
celebi/schema/__init__.py
celebi/schema/utils.py
celebi/types/__init__.py
celebi/types/datatype/__init__.py
celebi/types/datatype/datum.py