Metadata-Version: 1.0
Name: celebi
Version: 0.0.1
Summary: celebi is a Actor Based TS data anaylize engine
Home-page: UNKNOWN
Author: ryankung
Author-email: ryankung@ieee.org
License: GPL
Platform: UNKNOWN
